git_change_request/__init__.py
git_change_request/bin/__init__.py
git_change_request/bin/change_request_cli.py
git_change_request/src/__init__.py
git_change_request/src/exceptions.py
git_change_request/src/apis/__init__.py
git_change_request/src/apis/base_request.py
git_change_request/src/apis/change_request.py
git_change_request/src/apis/github_request.py
git_change_request/src/helpers/__init__.py
git_change_request/src/helpers/decorators.py
git_change_request/src/helpers/logger.py
git_change_request/src/helpers/packager.py
git_change_request-0.4.0.dist-info/LICENSE
git_change_request-0.4.0.dist-info/METADATA
git_change_request-0.4.0.dist-info/WHEEL
git_change_request-0.4.0.dist-info/entry_points.txt
git_change_request-0.4.0.dist-info/top_level.txt
git_change_request-0.4.0.dist-info/RECORD
