Metadata-Version: 2.1
Name: git-change-request
Version: 0.4.0
Summary: tool for working with pull/merge requests in a CI context.
Home-page: https://github.com/Dannyb48/git-change-request
Author: Danny Baez
Author-email: danny.baez.jr@gmail.com
License: GPLv3
Platform: UNKNOWN
Classifier: Programming Language :: Python :: 3
Classifier: License :: OSI Approved :: GNU General Public License v3 (GPLv3)
Classifier: Intended Audience :: Developers
Classifier: Topic :: Software Development :: Quality Assurance
Classifier: Topic :: Software Development :: Libraries :: Python Modules
Requires-Dist: PyGithub
Requires-Dist: GitPython
Requires-Dist: click
